apertium_init.py
apertium_init-3.0.0.dist-info/LICENSE
apertium_init-3.0.0.dist-info/METADATA
apertium_init-3.0.0.dist-info/WHEEL
apertium_init-3.0.0.dist-info/entry_points.txt
apertium_init-3.0.0.dist-info/top_level.txt
apertium_init-3.0.0.dist-info/RECORD
