Metadata-Version: 2.1
Name: apertium-init
Version: 3.0.0
Summary: Bootstrap Apertium language modules and pairs
Home-page: https://github.com/apertium/apertium-init
Author: Sushain K. Cherivirala
Author-email: sushain@skc.name
License: GPLv3+
Keywords: apertium parsing linguistics
Platform: UNKNOWN
Classifier: Development Status :: 5 - Production/Stable
Classifier: Topic :: Text Processing :: Linguistic
Classifier: License :: OSI Approved :: GNU General Public License v3 or later (GPLv3+)
Classifier: Intended Audience :: Science/Research
Classifier: Intended Audience :: Developers
Classifier: Programming Language :: Python :: 3.6
Classifier: Programming Language :: Python :: 3.7
Classifier: Programming Language :: Python :: 3.8
Classifier: Programming Language :: Python :: 3.9
Classifier: Programming Language :: Python :: 3 :: Only
Classifier: Programming Language :: Python :: Implementation :: CPython
Requires-Python: >=3.4
